Workbook

Sheet Overview
A1: Risk Assessment: Apex Financial Partners (Fictional Firm)
A3: Firm name: | B3: Apex Financial Partners
A4: Firm profile: | B4: 30-person financial advisory and accounting firm. Manages client investment accounts and tax records and uses a client portal, cloud CRM and accounting software, and a shared drive.
A6: Method
A7: 1. Identified 15 assets across data, systems, devices, network, people, and third parties
A8: 2. Paired each asset with a threat and a firm-specific exposure
A9: 3. Scored likelihood and impact on a 1-5 scale (score = likelihood x impact)
A10: 4. Tagged each risk with a NIST CSF 2.0 function and a treatment decision
A11: 5. Recommended a CIS Controls v8 safeguard for each risk
A13: Summary (updates automatically)
A15: Risks scored | B15: =COUNT('Risk Register'!G4:G18) -> 15
A16: Critical | B16: =COUNTIF('Risk Register'!H4:H18,"Critical") -> 2
A17: High | B17: =COUNTIF('Risk Register'!H4:H18,"High") -> 8
A18: Medium | B18: =COUNTIF('Risk Register'!H4:H18,"Medium") -> 5
A19: Low | B19: =COUNTIF('Risk Register'!H4:H18,"Low") -> 0
A20: (Fictional firm. All scores are my own judgments for a hypothetical organization.)

Sheet Scales
A1: Scoring Scales and Rating Bands
A3: Likelihood (1-5)
A4: 1 | B4: Rare | C4: Unlikely to happen in the next year
A5: 2 | B5: Unlikely | C5: Could happen, but not expected
A6: 3 | B6: Possible | C6: Might happen about once a year
A7: 4 | B7: Likely | C7: Expected to happen more than once a year
A8: 5 | B8: Almost certain | C8: Happening now or very frequently
A10: Impact (1-5)
A11: 1 | B11: Minimal | C11: Minor inconvenience, no real loss
A12: 2 | B12: Minor | C12: Short disruption, small cost
A13: 3 | B13: Moderate | C13: Noticeable disruption or cost; some clients affected
A14: 4 | B14: Major | C14: Serious disruption, large cost, or regulatory attention
A15: 5 | B15: Severe | C15: Business-threatening: major data breach, long outage, lost clients
A17: Rating bands (Risk Score = Likelihood x Impact)
A18: Rating | B18: Highest score in band
A19: Low | B19: 4
A20: Medium | B20: 9
A21: High | B21: 16
A22: Critical | B22: 25
A24: Assumption: band cutoffs (4 / 9 / 16 / 25) are a common 5x5 convention chosen as a starting point, not a standard. Edit the blue cells to change them; the register updates automatically.

Sheet Risk Register
A1: ="Risk Register - "&Overview!B3 -> Risk Register - Apex Financial Partners
A3: ID | B3: Asset | C3: Threat | D3: Why this firm is exposed | E3: Likelihood (1-5) | F3: Impact (1-5) | G3: Risk Score | H3: Rating | I3: NIST CSF 2.0 Function | J3: Treatment | K3: Recommended control (CIS Controls v8)
A4: R-01 | B4: CRM, cloud accounting, and billing software | C4: Unauthorized access to client records and payment details | D4: Shared logins and accounts of former staff aren't removed | E4: 3 | F4: 4 | G4: =IF(AND(ISNUMBER(E4),ISNUMBER(F4)),E4*F4,"") -> 12 | H4: =IF(G4="","",IF(G4<=Scales!$B$19,Scales!$A$19,IF(G4<=Scales!$B$20,Scales!$A$20,IF(G4<=Scales!$B$21,Scales!$A$21,Scales!$A$22)))) -> High | I4: Govern | J4: Mitigate | K4: CIS 5: remove accounts on offboarding
A5: R-02 | B5: Client personal and financial data | C5: Data breach and/or identity theft | D5: Stored in several places with no clear access limits | E5: 3 | F5: 5 | G5: =IF(AND(ISNUMBER(E5),ISNUMBER(F5)),E5*F5,"") -> 15 | H5: =IF(G5="","",IF(G5<=Scales!$B$19,Scales!$A$19,IF(G5<=Scales!$B$20,Scales!$A$20,IF(G5<=Scales!$B$21,Scales!$A$21,Scales!$A$22)))) -> High | I5: Protect | J5: Mitigate | K5: CIS 3 Data Protection: encrypt, limit access
A6: R-03 | B6: Client portal | C6: Account takeover using stolen passwords & credentials | D6: Clients log in with no MFA (Multi-factor Authentication) | E6: 4 | F6: 4 | G6: =IF(AND(ISNUMBER(E6),ISNUMBER(F6)),E6*F6,"") -> 16 | H6: =IF(G6="","",IF(G6<=Scales!$B$19,Scales!$A$19,IF(G6<=Scales!$B$20,Scales!$A$20,IF(G6<=Scales!$B$21,Scales!$A$21,Scales!$A$22)))) -> High | I6: Protect | J6: Mitigate | K6: CIS 6 Access Control: require MFA
A7: R-04 | B7: Email | C7: Phishing & corporate email compromise | D7: Emails containing sensitive information. No phishing training | E7: 5 | F7: 4 | G7: =IF(AND(ISNUMBER(E7),ISNUMBER(F7)),E7*F7,"") -> 20 | H7: =IF(G7="","",IF(G7<=Scales!$B$19,Scales!$A$19,IF(G7<=Scales!$B$20,Scales!$A$20,IF(G7<=Scales!$B$21,Scales!$A$21,Scales!$A$22)))) -> Critical | I7: Protect | J7: Mitigate | K7: CIS 9 Email Protections, CIS 14 phishing training
A8: R-05 | B8: Payroll and HR systems | C8: Stolen SSNs, payroll fraud, direct deposit details | D8: Changes to bank details aren't verified by a second person | E8: 3 | F8: 4 | G8: =IF(AND(ISNUMBER(E8),ISNUMBER(F8)),E8*F8,"") -> 12 | H8: =IF(G8="","",IF(G8<=Scales!$B$19,Scales!$A$19,IF(G8<=Scales!$B$20,Scales!$A$20,IF(G8<=Scales!$B$21,Scales!$A$21,Scales!$A$22)))) -> High | I8: Govern | J8: Mitigate | K8: CIS 6: second-person approval for bank changes
A9: R-06 | B9: Advisor laptops and phones | C9: Theft or loss with client data on the device | D9: Disks lacking full encryption. Frequent travel or remote work. | E9: 3 | F9: 4 | G9: =IF(AND(ISNUMBER(E9),ISNUMBER(F9)),E9*F9,"") -> 12 | H9: =IF(G9="","",IF(G9<=Scales!$B$19,Scales!$A$19,IF(G9<=Scales!$B$20,Scales!$A$20,IF(G9<=Scales!$B$21,Scales!$A$21,Scales!$A$22)))) -> High | I9: Protect | J9: Mitigate | K9: CIS 3: full-disk encryption
A10: R-07 | B10: USB and external drives | C10: Data copied, stolen, or malware installed | D10: No policy controls on external media | E10: 3 | F10: 3 | G10: =IF(AND(ISNUMBER(E10),ISNUMBER(F10)),E10*F10,"") -> 9 | H10: =IF(G10="","",IF(G10<=Scales!$B$19,Scales!$A$19,IF(G10<=Scales!$B$20,Scales!$A$20,IF(G10<=Scales!$B$21,Scales!$A$21,Scales!$A$22)))) -> Medium | I10: Protect | J10: Mitigate | K10: CIS 10 Malware Defenses: block removable media
A11: R-08 | B11: Shared drive and backups | C11: Ransomware encrypts files and backups | D11: Backups are never tested or restored | E11: 4 | F11: 5 | G11: =IF(AND(ISNUMBER(E11),ISNUMBER(F11)),E11*F11,"") -> 20 | H11: =IF(G11="","",IF(G11<=Scales!$B$19,Scales!$A$19,IF(G11<=Scales!$B$20,Scales!$A$20,IF(G11<=Scales!$B$21,Scales!$A$21,Scales!$A$22)))) -> Critical | I11: Recover | J11: Mitigate | K11: CIS 11 Data Recovery: offline backups, test restores
A12: R-09 | B12: VPN gateway | C12: Attackers exploit weak or vulnerable VPN, stolen credentials | D12: Remote access depends on a device that's rarely updated | E12: 3 | F12: 4 | G12: =IF(AND(ISNUMBER(E12),ISNUMBER(F12)),E12*F12,"") -> 12 | H12: =IF(G12="","",IF(G12<=Scales!$B$19,Scales!$A$19,IF(G12<=Scales!$B$20,Scales!$A$20,IF(G12<=Scales!$B$21,Scales!$A$21,Scales!$A$22)))) -> High | I12: Protect | J12: Mitigate | K12: CIS 7 Vulnerability Mgmt: patch on a schedule
A13: R-10 | B13: Domain name and DNS | C13: Domain hijacking or email spoofing | D13: Lack of MFA, no email authentication records | E13: 2 | F13: 4 | G13: =IF(AND(ISNUMBER(E13),ISNUMBER(F13)),E13*F13,"") -> 8 | H13: =IF(G13="","",IF(G13<=Scales!$B$19,Scales!$A$19,IF(G13<=Scales!$B$20,Scales!$A$20,IF(G13<=Scales!$B$21,Scales!$A$21,Scales!$A$22)))) -> Medium | I13: Protect | J13: Mitigate | K13: CIS 9: SPF/DKIM/DMARC, registrar MFA
A14: R-11 | B14: API keys and integration credentials | C14: A leaked key lets an attacker steal data or money | D14: Keys are never rotated | E14: 3 | F14: 4 | G14: =IF(AND(ISNUMBER(E14),ISNUMBER(F14)),E14*F14,"") -> 12 | H14: =IF(G14="","",IF(G14<=Scales!$B$19,Scales!$A$19,IF(G14<=Scales!$B$20,Scales!$A$20,IF(G14<=Scales!$B$21,Scales!$A$21,Scales!$A$22)))) -> High | I14: Protect | J14: Mitigate | K14: CIS 5 Account Mgmt: vault and rotate keys
A15: R-12 | B15: MFA tokens and authentication apps | C15: SIM swap, stolen phone, phished codes | D15: SMS codes are used and there's no backup process | E15: 3 | F15: 3 | G15: =IF(AND(ISNUMBER(E15),ISNUMBER(F15)),E15*F15,"") -> 9 | H15: =IF(G15="","",IF(G15<=Scales!$B$19,Scales!$A$19,IF(G15<=Scales!$B$20,Scales!$A$20,IF(G15<=Scales!$B$21,Scales!$A$21,Scales!$A$22)))) -> Medium | I15: Protect | J15: Mitigate | K15: CIS 6: app-based MFA, backup codes
... A18: R-15 | B18: Paper records and shredding bins | C18: Sensitive information on thrown out or unshredded paper | D18: Bins sit in a hallway and cleaners have after-hours access | E18: 2 | F18: 3 | G18: =IF(AND(ISNUMBER(E18),ISNUMBER(F18)),E18*F18,"") -> 6 | H18: =IF(G18="","",IF(G18<=Scales!$B$19,Scales!$A$19,IF(G18<=Scales!$B$20,Scales!$A$20,IF(G18<=Scales!$B$21,Scales!$A$21,Scales!$A$22)))) -> Medium | I18: Protect | J18: Mitigate | K18: CIS 3: locked bins, scheduled shredding
